chargebee_byte/__init__.py
chargebee_byte/client.py
chargebee_byte/parameters.py
chargebee_byte/requests.py
chargebee_byte-0.1.4.dist-info/LICENSE
chargebee_byte-0.1.4.dist-info/METADATA
chargebee_byte-0.1.4.dist-info/WHEEL
chargebee_byte-0.1.4.dist-info/top_level.txt
chargebee_byte-0.1.4.dist-info/RECORD
