Metadata-Version: 2.1
Name: chargebee-byte
Version: 0.1.4
Summary: Chargebee API library. Made by Byte.nl
Home-page: https://github.com/ByteInternet/chargebee-byte
Author: Byte
Author-email: tech@byte.nl
License: MIT
Platform: UNKNOWN
Classifier: Development Status :: 4 - Beta
Classifier: Intended Audience :: Developers
Classifier: Operating System :: POSIX
Classifier: Programming Language :: Python
Classifier: Programming Language :: Python :: 3.4
Classifier: Programming Language :: Python :: 3.5
Classifier: Programming Language :: Python :: 3.6
Classifier: Programming Language :: Python :: 3.7
License-File: LICENSE
Requires-Dist: requests
